{"metadata": {"dbt_schema_version": "https://schemas.getdbt.com/dbt/run-results/v4.json", "dbt_version": "1.0.4", "generated_at": "2022-03-29T15:50:10.660071Z", "invocation_id": "a8da490c-363b-4d64-880f-4d4a9e5061e1", "env": {}}, "results": [], "elapsed_time": 0.0, "args": {"write_json": true, "use_colors": true, "printer_width": 80, "version_check": true, "partial_parse": true, "static_parser": true, "profiles_dir": "/usr/src/develop/.dbt", "send_anonymous_usage_stats": true, "event_buffer_size": 100000, "vars": "{}\n", "which": "snapshot", "rpc_method": "snapshot", "indirect_selection": "eager"}}